atmdatatools/__init__.py
atmdatatools/adsb_tools.py
atmdatatools-0.0.1.dist-info/LICENSE
atmdatatools-0.0.1.dist-info/METADATA
atmdatatools-0.0.1.dist-info/WHEEL
atmdatatools-0.0.1.dist-info/top_level.txt
atmdatatools-0.0.1.dist-info/RECORD
