Metadata-Version: 2.1
Name: atmdatatools
Version: 0.0.1
Summary: Tools for air traffic data analysis
Author-email: Skyler Tan <shiuhtan123@gmail.com>
Project-URL: Homepage, https://github.com/skulu/ATM_datatools
Keywords: air,traffic,management,ADSB,ADS-B
Classifier: License :: OSI Approved :: GNU General Public License v3 (GPLv3)
Classifier: Programming Language :: Python
Classifier: Programming Language :: Python :: 3
Classifier: Development Status :: 2 - Pre-Alpha
Requires-Python: >=3.9
License-File: LICENSE
Requires-Dist: pandas (>=1.5.3)
Requires-Dist: geopandas (>=0.12.2)
Requires-Dist: shapely (>=2.0.1)
